markdown_to_png/__init__.py
markdown_to_png/convertor.py
markdown_to_png/tool.py
markdown_to_png-1.1.5.dist-info/METADATA
markdown_to_png-1.1.5.dist-info/WHEEL
markdown_to_png-1.1.5.dist-info/licenses/LICENSE
markdown_to_png-1.1.5.dist-info/RECORD
