Metadata-Version: 2.4
Name: markdown-to-png
Version: 1.1.5
Summary: A Python package designed to convert Markdown files into beautifully styled PNG images.
Project-URL: Homepage, https://github.com/richiepagard/markdown-to-png/
Project-URL: Issues, https://github.com/richiepagard/markdown-to-png/issues/
Author-email: Richie <richiepagard@gmail.com>
License-Expression: MIT
License-File: LICENSE
Classifier: Operating System :: POSIX :: Linux
Classifier: Programming Language :: Python :: 3
Requires-Python: >=3.8
Requires-Dist: imgkit>=1.2
Requires-Dist: markdown>=3.4
